{
    "code" : "success",
    "data" :     {
        "endRow" : 8,
        "hasNextPage" : 0,
        "hasPreviousPage" : 0,
        "isFirstPage" : 1,
        "isLastPage" : 1,
        "navigateFirstPage" : 1,
        "navigateLastPage" : 1,
        "navigatePages" : 8,
        "navigatepageNums" : 1,
        "nextPage" : 0,
        "pageNum" : 1,
        "pageSize" : 10,
        "pages" : 1,
        "prePage" : 0,
        "size" : 8,
        "startRow" : 1,
        "total" : 8,
        "list" :         [
            {
                "id": 3311,
                "name": "岩谷Iwatani户外瓦斯炉卡磁炉便携卡式炉防风燃气灶 野炊炉具炉子",
                "imgUrl": "https://g-search1.alicdn.com/img/bao/uploaded/i4/imgextra/i3/123841383/TB28CmztNuTBuNkHFNRXXc9qpXa_!!0-saturn_solar.jpg_360x360Q90.jpg_.webp",
                "price": "288.00",
                "carousels": [
                    {
                        "id": 1,
                        "url": "https://img.alicdn.com/imgextra/https://img.alicdn.com/imgextra/i4/3252009016/O1CN010mAexn2GTNV9ez9Df_!!3252009016.jpg_400x400q90.jpg"
                    },
                    {
                        "id": 2,
                        "url": "https://img.alicdn.com/imgextra/https://img.alicdn.com/imgextra/i1/3252009016/O1CN01dq98NH2GTNUmoh0SQ_!!3252009016.jpg_400x400q90.jpg"
                    },
                    {
                        "id": 3,
                        "url": "https://img.alicdn.com/imgextra/https://img.alicdn.com/imgextra/i4/3252009016/O1CN013J6STg2GTNUuLMbQL_!!3252009016.jpg_400x400q90.jpg"
                    },
                    {
                        "id": 4,
                        "url": "https://img.alicdn.com/imgextra/https://img.alicdn.com/imgextra/i3/3252009016/O1CN01ue1BWA2GTNUuphZyq_!!3252009016.jpg_400x400q90.jpg"
                    }
                ],
                "details": [
                    {
                        "id": 1,
                        "url": "https://img.alicdn.com/imgextra/i1/3252009016/O1CN015XkPqu2GTNUuSS4tk_!!3252009016.jpg"
                    },
                    {
                        "id": 2,
                        "url": "https://img.alicdn.com/imgextra/i4/3252009016/O1CN01NylQum2GTNVcQpf7E_!!3252009016.jpg"
                    },
                    {
                        "id": 3,
                        "url": "https://img.alicdn.com/imgextra/i4/3252009016/O1CN01kL2gYU2GTNUtTejJ0_!!3252009016.jpg"
                    },
                    {
                        "id": 4,
                        "url": "https://img.alicdn.com/imgextra/i4/3252009016/O1CN01oiZXRp2GTNUtFJsUG_!!3252009016.jpg"
                    },
                    {
                        "id": 5,
                        "url": "https://img.alicdn.com/imgextra/i3/3252009016/O1CN01CSoDJr2GTNUthz0HX_!!3252009016.jpg"
                    },
                    {
                        "id": 6,
                        "url": "https://img.alicdn.com/imgextra/i2/3252009016/O1CN01LY9uub2GTNUsvMirJ_!!3252009016.jpg"
                    },
                    {
                        "id": 7,
                        "url": "https://img.alicdn.com/imgextra/i4/3252009016/O1CN01t86ObZ2GTNUqLoFqV_!!3252009016.jpg"
                    },
                    {
                        "id": 8,
                        "url": "https://img.alicdn.com/imgextra/i2/3252009016/O1CN01gYyvV52GTNUuSSspf_!!3252009016.jpg"
                    },
                    {
                        "id": 9,
                        "url": "https://img.alicdn.com/imgextra/i2/3252009016/O1CN019OXY9e2GTNUtTfKia_!!3252009016.jpg"
                    },
                    {
                        "id": 10,
                        "url": "https://img.alicdn.com/imgextra/i3/3252009016/O1CN01w7neQh2GTNUsvMFkc_!!3252009016.jpg"
                    },
                    {
                        "id": 11,
                        "url": "https://img.alicdn.com/imgextra/i3/3252009016/O1CN01oQQMJA2GTNUrbJbmH_!!3252009016.jpg"
                    },
                    {
                        "id": 12,
                        "url": "https://img.alicdn.com/imgextra/i4/3252009016/O1CN013qESYc2GTNUuSTksM_!!3252009016.jpg"
                    },
                    {
                        "id": 13,
                        "url": "https://img.alicdn.com/imgextra/i2/3252009016/O1CN01Q9w1gz2GTNUrbJPHr_!!3252009016.jpg"
                    },
                    {
                        "id": 14,
                        "url": "https://img.alicdn.com/imgextra/i2/3252009016/O1CN01pzmHdN2GTNUqLmqaz_!!3252009016.jpg"
                    },
                    {
                        "id": 15,
                        "url": "https://img.alicdn.com/imgextra/i4/3252009016/O1CN01HgOMrW2GTNUti159X_!!3252009016.jpg"
                    },
                    {
                        "id": 16,
                        "url": "https://img.alicdn.com/imgextra/i3/3252009016/O1CN01qRr9xN2GTNUvFlzOW_!!3252009016.jpg"
                    },
                    {
                        "id": 17,
                        "url": "https://img.alicdn.com/imgextra/i1/3252009016/O1CN01NXTFO72GTNUvzTXBP_!!3252009016.jpg"
                    },
                    {
                        "id": 18,
                        "url": "https://img.alicdn.com/imgextra/i4/3252009016/O1CN01hMo9qG2GTNUtFJH66_!!3252009016.jpg"
                    }
                ]
            },
            {
                "id": 3312,
                "name": "岩谷 卡式炉专用箱便携箱手提箱 户外旅行家用野外野营便携式用品",
                "imgUrl": "https://g-search2.alicdn.com/img/bao/uploaded/i4/i1/1587439734/TB1Qn4wwWAoBKNjSZSyXXaHAVXa_!!0-item_pic.jpg_360x360Q90.jpg_.webp",
                "price": "45.00",
                "carousels": [
                    {
                        "id": 1,
                        "url": "https://img.alicdn.com/imgextra/i1/1587439734/TB1Qn4wwWAoBKNjSZSyXXaHAVXa_!!0-item_pic.jpg_400x400q90.jpg"
                    },
                    {
                        "id": 2,
                        "url": "https://img.alicdn.com/imgextra/i3/TB18ZqmMpXXXXafaXXXXXXXXXXX_!!0-item_pic.jpg_400x400q90.jpg"
                    },
                    {
                        "id": 3,
                        "url": "https://img.alicdn.com/imgextra/i4/1587439734/TB2A3y8mVXXXXaSXXXXXXXXXXXX_!!1587439734.jpg_400x400q90.jpg"
                    },
                    {
                        "id": 4,
                        "url": "https://img.alicdn.com/imgextra/i1/1587439734/TB2eHO.mVXXXXaGXXXXXXXXXXXX_!!1587439734.jpg_400x400q90.jpg"
                    },
                    {
                        "id": 5,
                        "url": "https://img.alicdn.com/imgextra/i1/1587439734/TB2MVGzmVXXXXccXpXXXXXXXXXX_!!1587439734.jpg_400x400q90.jpg"
                    }
                ],
                "details": [
                    {
                        "id": 1,
                        "url": "https://img.alicdn.com/imgextra/i4/1587439734/TB2KTqHmVXXXXaRXpXXXXXXXXXX_!!1587439734.jpg"
                    },
                    {
                        "id": 2,
                        "url": "https://img.alicdn.com/imgextra/i4/1587439734/TB2HVy.mVXXXXaKXXXXXXXXXXXX_!!1587439734.jpg"
                    },
                    {
                        "id": 3,
                        "url": "https://img.alicdn.com/imgextra/i1/1587439734/TB2EvffmVXXXXXTXXXXXXXXXXXX_!!1587439734.jpg"
                    },
                    {
                        "id": 4,
                        "url": "https://img.alicdn.com/imgextra/i2/1587439734/TB250WAmVXXXXbWXpXXXXXXXXXX_!!1587439734.jpg"
                    },
                    {
                        "id": 5,
                        "url": "https://img.alicdn.com/imgextra/i4/1587439734/TB2yJKAmVXXXXbWXpXXXXXXXXXX_!!1587439734.jpg"
                    },
                    {
                        "id": 6,
                        "url": "https://img.alicdn.com/imgextra/i3/1587439734/TB2Z6aPmVXXXXXRXpXXXXXXXXXX_!!1587439734.jpg"
                    },
                    {
                        "id": 7,
                        "url": "https://img.alicdn.com/imgextra/i3/1587439734/TB2zLvXmVXXXXaIXXXXXXXXXXXX_!!1587439734.jpg"
                    },
                    {
                        "id": 8,
                        "url": "https://img.alicdn.com/imgextra/i2/1587439734/TB2BJKDmVXXXXbgXpXXXXXXXXXX_!!1587439734.jpg"
                    },
                    {
                        "id": 9,
                        "url": "https://img.alicdn.com/imgextra/i2/1587439734/TB2c1a1mVXXXXcqXXXXXXXXXXXX_!!1587439734.jpg"
                    },
                    {
                        "id": 10,
                        "url": "https://img.alicdn.com/imgextra/i2/1587439734/TB28CevmVXXXXcFXpXXXXXXXXXX_!!1587439734.jpg"
                    },
                    {
                        "id": 11,
                        "url": "https://img.alicdn.com/imgextra/i2/1587439734/TB2FeuznpXXXXXsXXXXXXXXXXXX_!!1587439734.jpg"
                    },
                    {
                        "id": 12,
                        "url": "https://img.alicdn.com/imgextra/i3/1587439734/TB2GgeAnpXXXXXHXXXXXXXXXXXX_!!1587439734.jpg"
                    }
                ]
            },
            {
                "id": 3313,
                "name": "岩谷 韩式烤肉盘 野外户外卡式炉烧烤盘 圆形便携不粘锅铁板烧盘",
                "imgUrl": "https://g-search3.alicdn.com/img/bao/uploaded/i4/i1/2295271898/O1CN010sDNXL1PtKJuw3TFK_!!2295271898.jpg_360x360Q90.jpg_.webp",
                "price": "85.00",
                "carousels": [
                    {
                        "id": 1,
                        "url": "https://img.alicdn.com/bao/uploaded/i2/TB140wBxpY7gK0jSZKzSuuikpXa.jpg_400x400.jpg"
                    },
                    {
                        "id": 2,
                        "url": "https://gd3.alicdn.com/imgextra/i1/2295271898/O1CN010sDNXL1PtKJuw3TFK_!!2295271898.jpg_400x400.jpg_.webp"
                    },
                    {
                        "id": 3,
                        "url": "https://gd3.alicdn.com/imgextra/i3/2295271898/O1CN01hEemKf1PtKJuw2rrh_!!2295271898.jpg_400x400.jpg_.webp"
                    },
                    {
                        "id": 4,
                        "url": "https://gd3.alicdn.com/imgextra/i3/2295271898/O1CN01WajANz1PtKJweArAB_!!2295271898.jpg_400x400.jpg_.webp"
                    },
                    {
                        "id": 5,
                        "url": "https://gd3.alicdn.com/imgextra/i3/2295271898/O1CN0181xNPE1PtKJwfo5lx_!!2295271898.jpg_400x400.jpg_.webp"
                    },
                    {
                        "id": 6,
                        "url": "https://gd1.alicdn.com/imgextra/i1/2295271898/O1CN01a5mxjE1PtKJsGKfHY_!!2295271898.jpg_400x400.jpg_.webp"
                    }
                ],
                "details": [
                    {
                        "id": 1,
                        "url": "https://img.alicdn.com/imgextra/i3/2295271898/O1CN01d3fHd91PtKJxycTUq_!!2295271898.jpg"
                    },
                    {
                        "id": 2,
                        "url": "https://img.alicdn.com/imgextra/i4/2295271898/O1CN01L8F1gc1PtKJxycboG_!!2295271898.jpg"
                    },
                    {
                        "id": 3,
                        "url": "https://img.alicdn.com/imgextra/i2/2295271898/O1CN01P6poWR1PtKJsb5R3v_!!2295271898.jpg"
                    },
                    {
                        "id": 4,
                        "url": "https://img.alicdn.com/imgextra/i4/2295271898/O1CN01I5hEkl1PtKJrIy5UC_!!2295271898.jpg"
                    },
                    {
                        "id": 5,
                        "url": "https://img.alicdn.com/imgextra/i4/2295271898/O1CN01mazFdo1PtKJu5NNBW_!!2295271898.jpg"
                    },
                    {
                        "id": 6,
                        "url": "https://img.alicdn.com/imgextra/i4/2295271898/O1CN01rA6way1PtKJz2CbuO_!!2295271898.jpg"
                    },
                    {
                        "id": 7,
                        "url": "https://img.alicdn.com/imgextra/i3/2295271898/O1CN0181xNPE1PtKJwfo5lx_!!2295271898.jpg"
                    },
                    {
                        "id": 8,
                        "url": "https://img.alicdn.com/imgextra/i2/2295271898/O1CN01fgqaZy1PtKJsI59a5_!!2295271898.jpg"
                    },
                    {
                        "id": 9,
                        "url": "https://img.alicdn.com/imgextra/i2/2295271898/O1CN01pulZh11PtKJz3QTBj_!!2295271898.jpg"
                    }
                ]
            },
            {
                "id": 3314,
                "name": "新品岩谷多功能锅便携圆形烧烤盘不粘方形铁板烧餐厅美食炊具户外",
                "imgUrl": "https://g-search3.alicdn.com/img/bao/uploaded/i4/i1/691639605/O1CN011qI7vz2Kp8lJOV3Ei_!!691639605.jpg_360x360Q90.jpg_.webp",
                "price": "88.00",
                "carousels": [
                    {
                        "id": 1,
                        "url": "https://gd1.alicdn.com/imgextra/i4/691639605/O1CN011qI7vz2Kp8lJOV3Ei_!!691639605.jpg_400x400.jpg_.webp"
                    },
                    {
                        "id": 2,
                        "url": "https://gd2.alicdn.com/imgextra/i2/691639605/O1CN01lf74JF2Kp8lFyBAaz_!!691639605.jpg_400x400.jpg_.webp"
                    },
                    {
                        "id": 3,
                        "url": "https://gd1.alicdn.com/imgextra/i1/691639605/O1CN01kSbJvs2Kp8lI6a3E2_!!691639605.jpg_400x400.jpg_.webp"
                    },
                    {
                        "id": 4,
                        "url": "https://gd3.alicdn.com/imgextra/i3/691639605/O1CN01uROQks2Kp8lHhpPsx_!!691639605.jpg_400x400.jpg_.webp"
                    },
                    {
                        "id": 5,
                        "url": "https://gd4.alicdn.com/imgextra/i4/691639605/O1CN01soxcn12Kp8lI0aVlS_!!691639605.jpg_400x400.jpg_.webp"
                    }
                ],
                "details": [
                    {
                        "id": 1,
                        "url": "https://img.alicdn.com/imgextra/i1/691639605/O1CN01YWv8Wa2Kp8j5SWj8F_!!691639605.jpg"
                    },
                    {
                        "id": 2,
                        "url": "https://img.alicdn.com/imgextra/i3/691639605/O1CN01wUguf72Kp8lI0dXAx_!!691639605.jpg"
                    },
                    {
                        "id": 3,
                        "url": "https://img.alicdn.com/imgextra/i3/691639605/O1CN017eToPj2Kp8lGCSsXW_!!691639605.jpg"
                    },
                    {
                        "id": 4,
                        "url": "https://img.alicdn.com/imgextra/i3/691639605/O1CN01Fy9wrc2Kp8lLWVcSW_!!691639605.jpg"
                    },
                    {
                        "id": 5,
                        "url": "https://img.alicdn.com/imgextra/i2/691639605/O1CN01ufUN8Z2Kp8lHLhrJd_!!691639605.jpg"
                    },
                    {
                        "id": 6,
                        "url": "https://img.alicdn.com/imgextra/i2/691639605/O1CN01JwD2g22Kp8lGCTcG3_!!691639605.jpg"
                    },
                    {
                        "id": 7,
                        "url": "https://img.alicdn.com/imgextra/i3/691639605/O1CN01xT9xja2Kp8lL5OR4a_!!691639605.jpg"
                    },
                    {
                        "id": 8,
                        "url": "https://img.alicdn.com/imgextra/i3/691639605/O1CN01BAFY9J2Kp8lJOaYS1_!!691639605.jpg"
                    },
                    {
                        "id": 9,
                        "url": "https://img.alicdn.com/imgextra/i2/691639605/O1CN015tD5Pb2Kp8lFyFnuJ_!!691639605.jpg"
                    },
                    {
                        "id": 10,
                        "url": "https://img.alicdn.com/imgextra/i1/691639605/O1CN01GCxIgJ2Kp8lHLiGJ0_!!691639605.jpg"
                    },
                    {
                        "id": 11,
                        "url": "https://img.alicdn.com/imgextra/i3/691639605/O1CN01iFBbWM2Kp8lI0fPbT_!!691639605.jpg"
                    },
                    {
                        "id": 12,
                        "url": "https://img.alicdn.com/imgextra/i2/691639605/O1CN01PSZfZN2Kp8lLWWYhb_!!691639605.jpg"
                    },
                    {
                        "id": 13,
                        "url": "https://img.alicdn.com/imgextra/i4/691639605/TB2sdv7jpkoBKNjSZFkXXb4tFXa_!!691639605.jpg"
                    }
                ]
            },
            {
                "id": 3315,
                "name": "新品岩谷多功能锅便携圆形烧烤盘不粘方形铁板烧户外餐厅美食炊具",
                "imgUrl": "https://g-search1.alicdn.com/img/bao/uploaded/i4/i1/2582507010/O1CN01mzygkV21ecyGHxMhV_!!2582507010.jpg_360x360Q90.jpg_.webp",
                "price": "85.00",
                "carousels": [
                    {
                        "id": 1,
                        "url": "https://gd1.alicdn.com/imgextra/i4/2582507010/O1CN01mzygkV21ecyGHxMhV_!!2582507010.jpg_400x400.jpg_.webp"
                    },
                    {
                        "id": 2,
                        "url": "https://gd1.alicdn.com/imgextra/i1/2582507010/O1CN01yBO0JG21ecyGHwIDs_!!2582507010.jpg_400x400.jpg_.webp"
                    },
                    {
                        "id": 3,
                        "url": "https://gd3.alicdn.com/imgextra/i3/2582507010/O1CN01n8P1uX21ecyGgddEd_!!2582507010.jpg_400x400.jpg_.webp"
                    },
                    {
                        "id": 4,
                        "url": "https://gd1.alicdn.com/imgextra/i1/2582507010/O1CN013zmXUB21ecyHrJIjU_!!2582507010.jpg_400x400.jpg_.webp"
                    },
                    {
                        "id": 5,
                        "url": "https://gd3.alicdn.com/imgextra/i3/2582507010/O1CN01EtYDpk21ecyHygQB0_!!2582507010.jpg_400x400.jpg_.webp"
                    }
                ],
                "details": [
                    {
                        "id": 1,
                        "url": "https://img.alicdn.com/imgextra/i3/2582507010/O1CN01btNNeI21ecw6FwBvT_!!2582507010.jpg"
                    },
                    {
                        "id": 2,
                        "url": "https://img.alicdn.com/imgextra/i2/2582507010/O1CN01OOzgBQ21ecyFvkEe3_!!2582507010.jpg"
                    },
                    {
                        "id": 3,
                        "url": "https://img.alicdn.com/imgextra/i3/2582507010/O1CN01CgDpdh21ecyJfQsRt_!!2582507010.jpg"
                    },
                    {
                        "id": 4,
                        "url": "https://img.alicdn.com/imgextra/i2/2582507010/O1CN01MKRcVH21ecyHLw8qw_!!2582507010.jpg"
                    },
                    {
                        "id": 5,
                        "url": "https://img.alicdn.com/imgextra/i1/2582507010/O1CN011M0U8t21ecyGaj3wO_!!2582507010.jpg"
                    },
                    {
                        "id": 6,
                        "url": "https://img.alicdn.com/imgextra/i2/2582507010/O1CN01fCppyF21ecyHydbJH_!!2582507010.jpg"
                    },
                    {
                        "id": 7,
                        "url": "https://img.alicdn.com/imgextra/i2/2582507010/O1CN01Y6O0Fs21ecyGahzR0_!!2582507010.jpg"
                    },
                    {
                        "id": 8,
                        "url": "https://img.alicdn.com/imgextra/i2/2582507010/O1CN01Zekn9s21ecyK6a8oi_!!2582507010.jpg"
                    },
                    {
                        "id": 9,
                        "url": "https://img.alicdn.com/imgextra/i3/2582507010/O1CN01dAQZR521ecy90NtDg_!!2582507010.jpg"
                    },
                    {
                        "id": 10,
                        "url": "https://img.alicdn.com/imgextra/i4/2582507010/O1CN01WnbvLR21ecyEmVaaH_!!2582507010.jpg"
                    },
                    {
                        "id": 11,
                        "url": "https://img.alicdn.com/imgextra/i4/2582507010/O1CN01e9DLl921ecyEmVvMA_!!2582507010.jpg"
                    },
                    {
                        "id": 12,
                        "url": "https://img.alicdn.com/imgextra/i1/2582507010/O1CN01CWFjK021ecyK6Z0Ca_!!2582507010.jpg"
                    },
                    {
                        "id": 13,
                        "url": "https://img.alicdn.com/imgextra/i2/2582507010/TB2IKXYAUR1BeNjy0FmXXb0wVXa_!!2582507010.jpg"
                    }
                ]
            },
            {
                "id": 3316,
                "name": "岩谷卡式炉家用户外炉具火锅炉便携式燃气炉卡磁炉煤气瓦斯猛火灶",
                "imgUrl": "https://g-search3.alicdn.com/img/bao/uploaded/i4/i2/1587439734/O1CN015GaJ0f2LmDtSPocND_!!0-item_pic.jpg_360x360Q90.jpg_.webp",
                "price": "130.00",
                "carousels": [
                    {
                        "id": 1,
                        "url": "https://img.alicdn.com/imgextra/https://img.alicdn.com/imgextra/i4/1587439734/O1CN01d9H7NL2LmDtOJArmM_!!1587439734.jpg_400x400q90.jpg"
                    },
                    {
                        "id": 2,
                        "url": "https://img.alicdn.com/imgextra/https://img.alicdn.com/imgextra/i1/1587439734/O1CN01m4v52w2LmDsQYVRnK_!!1587439734.jpg_400x400q90.jpg"
                    },
                    {
                        "id": 3,
                        "url": "https://img.alicdn.com/imgextra/https://img.alicdn.com/imgextra/i2/1587439734/O1CN01LNREWX2LmDsOEsK4A_!!1587439734.jpg_400x400q90.jpg"
                    },
                    {
                        "id": 4,
                        "url": "https://img.alicdn.com/imgextra/https://img.alicdn.com/imgextra/i2/1587439734/O1CN01SnRzdW2LmDsRe7BqM_!!1587439734.jpg_400x400q90.jpg"
                    },
                    {
                        "id": 5,
                        "url": "https://img.alicdn.com/imgextra/https://img.alicdn.com/imgextra/i4/1587439734/O1CN01d8mk4x2LmDsNy01DU_!!1587439734.jpg_400x400q90.jpg"
                    }
                ],
                "details": [
                    {
                        "id": 1,
                        "url": "https://img.alicdn.com/imgextra/i1/1587439734/O1CN01mjYeEF2LmDsGArzOt_!!1587439734.jpg"
                    },
                    {
                        "id": 2,
                        "url": "https://img.alicdn.com/imgextra/i4/1587439734/O1CN01ioYreP2LmDsOEckLn_!!1587439734.jpg"
                    },
                    {
                        "id": 3,
                        "url": "https://img.alicdn.com/imgextra/i4/1587439734/O1CN01cq9hNe2LmDsM4YtCW_!!1587439734.jpg"
                    },
                    {
                        "id": 4,
                        "url": "https://img.alicdn.com/imgextra/i4/1587439734/O1CN01f0gge82LmDsR5LVFH_!!1587439734.jpg"
                    },
                    {
                        "id": 5,
                        "url": "https://img.alicdn.com/imgextra/i3/1587439734/O1CN01OXzSSq2LmDsODeWtb_!!1587439734.jpg"
                    },
                    {
                        "id": 6,
                        "url": "https://img.alicdn.com/imgextra/i2/1587439734/O1CN01Uz3KlP2LmDsS61WEt_!!1587439734.jpg"
                    },
                    {
                        "id": 7,
                        "url": "https://img.alicdn.com/imgextra/i1/1587439734/O1CN010Om9as2LmDsLoQBDM_!!1587439734.jpg"
                    },
                    {
                        "id": 8,
                        "url": "https://img.alicdn.com/imgextra/i3/1587439734/O1CN011TEvND2LmDsLoOVHP_!!1587439734.jpg"
                    },
                    {
                        "id": 9,
                        "url": "https://img.alicdn.com/imgextra/i2/1587439734/O1CN01AQ8Lwr2LmDsNkdWUw_!!1587439734.jpg"
                    },
                    {
                        "id": 10,
                        "url": "https://img.alicdn.com/imgextra/i2/1587439734/O1CN019HymeY2LmDsPmkx9z_!!1587439734.jpg"
                    },
                    {
                        "id": 11,
                        "url": "https://img.alicdn.com/imgextra/i2/1587439734/O1CN01jKr43l2LmDsRdo7ua_!!1587439734.jpg"
                    },
                    {
                        "id": 12,
                        "url": "https://img.alicdn.com/imgextra/i1/1587439734/O1CN01NRUKgy2LmDsNxk6gv_!!1587439734.jpg"
                    },
                    {
                        "id": 13,
                        "url": "https://img.alicdn.com/imgextra/i4/1587439734/O1CN01RXIOQv2LmDsLoPucq_!!1587439734.jpg"
                    },
                    {
                        "id": 14,
                        "url": "https://img.alicdn.com/imgextra/i3/1587439734/O1CN01XfyleH2LmDsPdO6TJ_!!1587439734.jpg"
                    },
                    {
                        "id": 15,
                        "url": "https://img.alicdn.com/imgextra/i3/1587439734/O1CN01RuXLHH2LmDsPdPB0Y_!!1587439734.jpg"
                    },
                    {
                        "id": 16,
                        "url": "https://img.alicdn.com/imgextra/i1/1587439734/O1CN01XGUJZm2LmDsODeObo_!!1587439734.jpg"
                    },
                    {
                        "id": 17,
                        "url": "https://img.alicdn.com/imgextra/i4/1587439734/O1CN012CxnFb2LmDsLoQaAa_!!1587439734.jpg"
                    },
                    {
                        "id": 18,
                        "url": "https://img.alicdn.com/imgextra/i4/1587439734/O1CN010bFmkN2LmDsRdq8e2_!!1587439734.jpg"
                    },
                    {
                        "id": 19,
                        "url": "https://img.alicdn.com/imgextra/i2/1587439734/O1CN01se57Xv2LmDt8Glqbe_!!1587439734.jpg"
                    },
                    {
                        "id": 20,
                        "url": "https://img.alicdn.com/imgextra/i4/1587439734/O1CN01s77DKj2LmDsPdRK2O_!!1587439734.jpg"
                    },
                    {
                        "id": 21,
                        "url": "https://img.alicdn.com/imgextra/i4/1587439734/O1CN01jsTRtB2LmDsKq4F1k_!!1587439734.jpg"
                    },
                    {
                        "id": 22,
                        "url": "https://img.alicdn.com/imgextra/i3/1587439734/O1CN01u6VyOS2LmDsOz6Mf8_!!1587439734.jpg"
                    },
                    {
                        "id": 23,
                        "url": "https://img.alicdn.com/imgextra/i1/1587439734/O1CN01sn4sR22LmDsGArmyY_!!1587439734.jpg"
                    },
                    {
                        "id": 24,
                        "url": "https://img.alicdn.com/imgextra/i3/1587439734/O1CN01XRboUQ2LmDrvWRwVL_!!1587439734.jpg"
                    },
                    {
                        "id": 25,
                        "url": "https://img.alicdn.com/imgextra/i3/1587439734/O1CN01Vk4ASb2LmDs1dHI1C_!!1587439734.jpg"
                    },
                    {
                        "id": 26,
                        "url": "https://img.alicdn.com/imgextra/i4/1587439734/O1CN01RjQGXm2LmDrAaODWa_!!1587439734.jpg"
                    },
                    {
                        "id": 27,
                        "url": "https://img.alicdn.com/imgextra/i1/1587439734/O1CN01Scv2Ih2LmDrBF5fGc_!!1587439734.jpg"
                    },
                    {
                        "id": 28,
                        "url": "https://img.alicdn.com/imgextra/i2/1587439734/O1CN01FBSpMj2LmDrD9Tgai_!!1587439734.jpg"
                    },
                    {
                        "id": 29,
                        "url": "https://img.alicdn.com/imgextra/i4/1587439734/O1CN01a0kxQz2LmDrDbJVhg_!!1587439734.jpg"
                    },
                    {
                        "id": 30,
                        "url": "https://img.alicdn.com/imgextra/i1/1587439734/O1CN01ByKlRp2LmDrA9aMTu_!!1587439734.jpg"
                    },
                    {
                        "id": 31,
                        "url": "https://img.alicdn.com/imgextra/i4/1587439734/O1CN01BWxq8e2LmDrBw2cqe_!!1587439734.jpg"
                    },
                    {
                        "id": 32,
                        "url": "https://img.alicdn.com/imgextra/i2/1587439734/O1CN01ct5wUM2LmDr7T7hpq_!!1587439734.jpg"
                    },
                    {
                        "id": 33,
                        "url": "https://img.alicdn.com/imgextra/i4/1587439734/O1CN01iBddJJ2LmDrAaSJCF_!!1587439734.jpg"
                    },
                    {
                        "id": 34,
                        "url": "https://img.alicdn.com/imgextra/i1/1587439734/O1CN01RQQrbN2LmDrAaPUZd_!!1587439734.jpg"
                    },
                    {
                        "id": 35,
                        "url": "https://img.alicdn.com/imgextra/i2/1587439734/O1CN01TthKxZ2LmDrA9Zl8H_!!1587439734.jpg"
                    },
                    {
                        "id": 36,
                        "url": "https://img.alicdn.com/imgextra/i4/1587439734/O1CN01Hm3wPu2LmDrAU1mYQ_!!1587439734.jpg"
                    },
                    {
                        "id": 37,
                        "url": "https://img.alicdn.com/imgextra/i3/1587439734/O1CN01nATnI72LmDrAaR6Oa_!!1587439734.jpg"
                    },
                    {
                        "id": 38,
                        "url": "https://img.alicdn.com/imgextra/i2/1587439734/O1CN01XequYq2LmDrD9TcTl_!!1587439734.jpg"
                    },
                    {
                        "id": 39,
                        "url": "https://img.alicdn.com/imgextra/i3/1587439734/O1CN01TWF4Pt2LmDrAaRq7V_!!1587439734.jpg"
                    },
                    {
                        "id": 40,
                        "url": "https://img.alicdn.com/imgextra/i4/1587439734/O1CN01Y11K0V2LmDrBmI91u_!!1587439734.jpg"
                    },
                    {
                        "id": 41,
                        "url": "https://img.alicdn.com/imgextra/i4/1587439734/O1CN01MzfBgr2LmDrAaRq7y_!!1587439734.jpg"
                    },
                    {
                        "id": 42,
                        "url": "https://img.alicdn.com/imgextra/i1/1587439734/O1CN01hANxor2LmDrAU1qjs_!!1587439734.jpg"
                    },
                    {
                        "id": 43,
                        "url": "https://img.alicdn.com/imgextra/i1/1587439734/O1CN01nP8Rkn2LmDrATylS7_!!1587439734.jpg"
                    },
                    {
                        "id": 44,
                        "url": "https://img.alicdn.com/imgextra/i1/1587439734/O1CN01i3LU4d2LmDr7T6AGv_!!1587439734.jpg"
                    }
                ]
            },
            {
                "id": 3317,
                "name": "岩谷 户外专用便携卡式炉野炊燃气炉瓦斯炉防风炉具 猛火3.5KW",
                "imgUrl": "https://g-search2.alicdn.com/img/bao/uploaded/i4/i1/3016724357/O1CN01buWDul1i3YFNh9COo_!!0-item_pic.jpg_360x360Q90.jpg_.webp",
                "price": "358.00",
                "carousels": [
                    {
                        "id": 1,
                        "url": "https://img.alicdn.com/imgextra/https://img.alicdn.com/imgextra/i2/3016724357/O1CN01Px6OV61i3YFQABvWz_!!3016724357.jpg_400x400q90.jpg"
                    },
                    {
                        "id": 2,
                        "url": "https://img.alicdn.com/imgextra/https://img.alicdn.com/imgextra/i2/3016724357/O1CN010tTwbl1i3YCv3FgGJ_!!3016724357.jpg_400x400q90.jpg"
                    },
                    {
                        "id": 3,
                        "url": "https://img.alicdn.com/imgextra/https://img.alicdn.com/imgextra/i4/3016724357/O1CN01vcoksQ1i3YCutzbV0_!!3016724357.jpg_400x400q90.jpg"
                    },
                    {
                        "id": 4,
                        "url": "https://img.alicdn.com/imgextra/https://img.alicdn.com/imgextra/i1/3016724357/O1CN01S8Dqxl1i3YCt9sVC3_!!3016724357.jpg_400x400q90.jpg"
                    },
                    {
                        "id": 5,
                        "url": "https://img.alicdn.com/imgextra/https://img.alicdn.com/imgextra/i2/3016724357/O1CN01S3tGhW1i3YCx30Yke_!!3016724357.jpg_400x400q90.jpg"
                    }
                ],
                "details": [
                    {
                        "id": 1,
                        "url": "https://img.alicdn.com/imgextra/i4/3016724357/O1CN01btLdog1i3YDvicm5i_!!3016724357.jpg"
                    },
                    {
                        "id": 2,
                        "url": "https://img.alicdn.com/imgextra/i3/3016724357/O1CN01IFSUrs1i3YDnmfmcZ_!!3016724357.jpg"
                    },
                    {
                        "id": 3,
                        "url": "https://img.alicdn.com/imgextra/i1/3016724357/O1CN01oSMG7x1i3YDvFr4YZ_!!3016724357.jpg"
                    },
                    {
                        "id": 4,
                        "url": "https://img.alicdn.com/imgextra/i2/3016724357/O1CN01HxMIxE1i3YDtc3tOp_!!3016724357.jpg"
                    },
                    {
                        "id": 5,
                        "url": "https://img.alicdn.com/imgextra/i2/3016724357/O1CN01AR9NM11i3YDz1OeBr_!!3016724357.jpg"
                    },
                    {
                        "id": 6,
                        "url": "https://img.alicdn.com/imgextra/i2/3016724357/O1CN01Sctb391i3YDz1Oqfj_!!3016724357.jpg"
                    },
                    {
                        "id": 7,
                        "url": "https://img.alicdn.com/imgextra/i1/3016724357/O1CN013axZFA1i3YDxDp2hY_!!3016724357.jpg"
                    },
                    {
                        "id": 8,
                        "url": "https://img.alicdn.com/imgextra/i1/3016724357/O1CN01FlFKOP1i3YDzV6geH_!!3016724357.jpg"
                    },
                    {
                        "id": 9,
                        "url": "https://img.alicdn.com/imgextra/i1/3016724357/O1CN01vJKYxY1i3YDvibZFh_!!3016724357.jpg"
                    },
                    {
                        "id": 10,
                        "url": "https://img.alicdn.com/imgextra/i4/3016724357/O1CN01iBE3PO1i3YDyW1xd1_!!3016724357.jpg"
                    },
                    {
                        "id": 11,
                        "url": "https://img.alicdn.com/imgextra/i3/3016724357/O1CN01beGjZM1i3YDwRanw8_!!3016724357.jpg"
                    }
                ]
            },
            {
                "id": 3318,
                "name": "日本进口岩谷卡式炉 便携式户外烧烤炉 卡磁炉家用卡斯野外瓦斯炉",
                "imgUrl": "https://g-search1.alicdn.com/img/bao/uploaded/i4/i4/3016724357/O1CN01Kl1IFV1i3YFOiAA1h_!!0-item_pic.jpg_360x360Q90.jpg_.webp",
                "price": "358.00",
                "carousels": [
                    {
                        "id": 1,
                        "url": "https://img.alicdn.com/imgextra/https://img.alicdn.com/imgextra/i2/3016724357/O1CN013SESrw1i3YFOYoaZy_!!3016724357.jpg_400x400q90.jpg"
                    },
                    {
                        "id": 2,
                        "url": "https://img.alicdn.com/imgextra/https://img.alicdn.com/imgextra/i2/3016724357/O1CN01Px9WHr1i3Y8P2s5ER_!!3016724357.jpg_400x400q90.jpg"
                    },
                    {
                        "id": 3,
                        "url": "https://img.alicdn.com/imgextra/https://img.alicdn.com/imgextra/i2/3016724357/O1CN01Zkciwy1i3Y8R6FoFj_!!3016724357.jpg_400x400q90.jpg"
                    },
                    {
                        "id": 4,
                        "url": "https://img.alicdn.com/imgextra/https://img.alicdn.com/imgextra/i4/3016724357/O1CN01ovgRsH1i3YFAjxFMK_!!3016724357.jpg_400x400q90.jpg"
                    },
                    {
                        "id": 5,
                        "url": "https://img.alicdn.com/imgextra/https://img.alicdn.com/imgextra/i2/3016724357/O1CN01qwsIvt1i3YF9R00Lv_!!3016724357.jpg_400x400q90.jpg"
                    }
                ],
                "details": [
                    {
                        "id": 1,
                        "url": "https://img.alicdn.com/imgextra/i1/3016724357/O1CN01p17F1N1i3YDv0vtPb_!!3016724357.jpg"
                    },
                    {
                        "id": 2,
                        "url": "https://img.alicdn.com/imgextra/i4/3016724357/O1CN017qfwkH1i3YDsUnpwv_!!3016724357.jpg"
                    },
                    {
                        "id": 3,
                        "url": "https://img.alicdn.com/imgextra/i4/3016724357/O1CN019Nq1mv1i3YDy0tVYg_!!3016724357.jpg"
                    },
                    {
                        "id": 4,
                        "url": "https://img.alicdn.com/imgextra/i3/3016724357/O1CN01kAxajB1i3YDvZUgPl_!!3016724357.jpg"
                    },
                    {
                        "id": 5,
                        "url": "https://img.alicdn.com/imgextra/i4/3016724357/O1CN01UDtBro1i3YDzYn4pN_!!3016724357.jpg"
                    },
                    {
                        "id": 6,
                        "url": "https://img.alicdn.com/imgextra/i2/3016724357/O1CN01vQWRpl1i3YDvmpBWH_!!3016724357.jpg"
                    },
                    {
                        "id": 7,
                        "url": "https://img.alicdn.com/imgextra/i1/3016724357/O1CN016cgQyY1i3YDtS845c_!!3016724357.jpg"
                    },
                    {
                        "id": 8,
                        "url": "https://img.alicdn.com/imgextra/i4/3016724357/O1CN01EP1F7C1i3YDxHVQrL_!!3016724357.jpg"
                    },
                    {
                        "id": 9,
                        "url": "https://img.alicdn.com/imgextra/i2/3016724357/O1CN01QEEFV71i3YDsUpB9p_!!3016724357.jpg"
                    }
                ]
            },
            {
                "id": 3319,
                "name": "岩谷卡式炉便携式燃气炉卡斯卡磁瓦斯炉家用野炊户外炉具火锅炉子",
                "imgUrl": "https://g-search3.alicdn.com/img/bao/uploaded/i4/i1/2453801130/O1CN01bQjtro1KDa8lADK1V_!!0-item_pic.jpg_360x360Q90.jpg_.webp",
                "price": "119.00",
                "carousels": [
                    {
                        "id": 1,
                        "url": "https://img.alicdn.com/imgextra/https://img.alicdn.com/imgextra/i3/2453801130/O1CN01RB6VSy1KDa8qvnBHq_!!2453801130.jpg_400x400q90.jpg"
                    },
                    {
                        "id": 2,
                        "url": "https://img.alicdn.com/imgextra/https://img.alicdn.com/imgextra/i4/2453801130/O1CN01Qu1L4g1KDa8lInYp4_!!2453801130.jpg_400x400q90.jpg"
                    },
                    {
                        "id": 3,
                        "url": "https://img.alicdn.com/imgextra/https://img.alicdn.com/imgextra/i3/2453801130/O1CN013dOi5q1KDa7ZebtN0_!!2453801130.jpg_400x400q90.jpg"
                    },
                    {
                        "id": 4,
                        "url": "https://img.alicdn.com/imgextra/https://img.alicdn.com/imgextra/i1/2453801130/O1CN017SCxGI1KDa7aRS0A4_!!2453801130.jpg_400x400q90.jpg"
                    },
                    {
                        "id": 5,
                        "url": "https://img.alicdn.com/imgextra/https://img.alicdn.com/imgextra/i2/2453801130/O1CN01dJD4a01KDa7dF9v0X_!!2453801130.jpg_400x400q90.jpg"
                    }
                ],
                "details": [
                    {
                        "id": 1,
                        "url": "https://img.alicdn.com/imgextra/i3/2453801130/O1CN01tvAych1KDa8Hbmsot_!!2453801130.jpg"
                    },
                    {
                        "id": 2,
                        "url": "https://img.alicdn.com/imgextra/i4/2453801130/O1CN01pfwnh81KDa77LLMDT_!!2453801130.jpg"
                    },
                    {
                        "id": 3,
                        "url": "https://img.alicdn.com/imgextra/i3/2453801130/O1CN01XW1VF31KDa7ELPlIf_!!2453801130.jpg"
                    },
                    {
                        "id": 4,
                        "url": "https://img.alicdn.com/imgextra/i4/2453801130/O1CN01iUTUJz1KDa76oKgyl_!!2453801130.jpg"
                    },
                    {
                        "id": 5,
                        "url": "https://img.alicdn.com/imgextra/i4/2453801130/O1CN01KZ5s4m1KDa75eSZQI_!!2453801130.jpg"
                    },
                    {
                        "id": 6,
                        "url": "https://img.alicdn.com/imgextra/i3/2453801130/O1CN01y8xJMb1KDa75eRpgJ_!!2453801130.jpg"
                    },
                    {
                        "id": 7,
                        "url": "https://img.alicdn.com/imgextra/i1/2453801130/O1CN01qdwU2Z1KDa75w10lD_!!2453801130.jpg"
                    },
                    {
                        "id": 8,
                        "url": "https://img.alicdn.com/imgextra/i4/2453801130/O1CN01GTxqW31KDa79idGUm_!!2453801130.jpg"
                    },
                    {
                        "id": 9,
                        "url": "https://img.alicdn.com/imgextra/i2/2453801130/O1CN01hlmogM1KDa79Hb79o_!!2453801130.jpg"
                    },
                    {
                        "id": 10,
                        "url": "https://img.alicdn.com/imgextra/i1/2453801130/O1CN01Q7TkoV1KDa742gjIq_!!2453801130.jpg"
                    },
                    {
                        "id": 11,
                        "url": "https://img.alicdn.com/imgextra/i3/2453801130/O1CN01EmDAsN1KDa6yItda8_!!2453801130.jpg"
                    },
                    {
                        "id": 12,
                        "url": "https://img.alicdn.com/imgextra/i4/2453801130/O1CN01eQX5v41KDa75eSAVW_!!2453801130.jpg"
                    },
                    {
                        "id": 13,
                        "url": "https://img.alicdn.com/imgextra/i4/2453801130/O1CN01iXPHmO1KDa764JkM3_!!2453801130.jpg"
                    },
                    {
                        "id": 14,
                        "url": "https://img.alicdn.com/imgextra/i2/2453801130/O1CN01ZwQZDO1KDa79ifXrW_!!2453801130.jpg"
                    },
                    {
                        "id": 15,
                        "url": "https://img.alicdn.com/imgextra/i3/2453801130/O1CN01DXqwHW1KDa76oJHnv_!!2453801130.jpg"
                    },
                    {
                        "id": 16,
                        "url": "https://img.alicdn.com/imgextra/i1/2453801130/O1CN01dWTc8p1KDa78I6obv_!!2453801130.jpg"
                    },
                    {
                        "id": 17,
                        "url": "https://img.alicdn.com/imgextra/i2/2453801130/O1CN01j107be1KDa77XgUTu_!!2453801130.jpg"
                    },
                    {
                        "id": 18,
                        "url": "https://img.alicdn.com/imgextra/i1/2453801130/O1CN01YzezKP1KDa80XhzdC_!!2453801130.jpg"
                    },
                    {
                        "id": 19,
                        "url": "https://img.alicdn.com/imgextra/i1/2453801130/O1CN01C24Svz1KDa78I5L6h_!!2453801130.jpg"
                    },
                    {
                        "id": 20,
                        "url": "https://img.alicdn.com/imgextra/i3/2453801130/O1CN01cvLogQ1KDa75MogHC_!!2453801130.jpg"
                    }
                ]
            },
            {
                "id": 3320,
                "name": "岩谷户外便携式卡式炉卡磁炉瓦斯炉家用炉超性价比",
                "imgUrl": "https://g-search1.alicdn.com/img/bao/uploaded/i4/imgextra/i2/27366388/O1CN01hd06JV1x3ke9FBu8A_!!0-saturn_solar.jpg_360x360Q90.jpg_.webp",
                "price": "99.00",
                "carousels": [
                    {
                        "id": 1,
                        "url": "https://gd3.alicdn.com/imgextra/i3/112239980/O1CN0133dEkQ2NatIXvA40C_!!112239980.jpg_400x400.jpg_.webp"
                    },
                    {
                        "id": 2,
                        "url": "https://gd4.alicdn.com/imgextra/i4/112239980/O1CN01mLoPHG2NatIUk1559_!!112239980.jpg_400x400.jpg_.webp"
                    },
                    {
                        "id": 3,
                        "url": "https://gd4.alicdn.com/imgextra/i4/112239980/O1CN01aliSDj2NatIT8B4y5_!!112239980.jpg_400x400.jpg_.webp"
                    },
                    {
                        "id": 4,
                        "url": "https://gd4.alicdn.com/imgextra/i4/112239980/O1CN017l50qc2NatIRxQAtz_!!112239980.jpg_400x400.jpg_.webp"
                    },
                    {
                        "id": 5,
                        "url": "https://gd2.alicdn.com/imgextra/i2/112239980/O1CN013RG4Sf2NatIRxQ2bS_!!112239980.jpg_400x400.jpg_.webp"
                    }
                ],
                "details": [
                    {
                        "id": 1,
                        "url": "https://img.alicdn.com/imgextra/i2/112239980/O1CN012NatCpTojAcfRSd_!!112239980.jpg"
                    },
                    {
                        "id": 2,
                        "url": "https://img.alicdn.com/imgextra/i2/112239980/O1CN01z6Mo452NatISvIRXu_!!112239980.jpg"
                    },
                    {
                        "id": 3,
                        "url": "https://img.alicdn.com/imgextra/i3/112239980/O1CN01BV7KDc2NatIV1QvXv_!!112239980.jpg"
                    },
                    {
                        "id": 4,
                        "url": "https://img.alicdn.com/imgextra/i1/112239980/O1CN01WTpHUP2NatIWdwAYY_!!112239980.jpg"
                    },
                    {
                        "id": 5,
                        "url": "https://img.alicdn.com/imgextra/i3/112239980/O1CN01PuujEZ2NatIVD4pz8_!!112239980.jpg"
                    },
                    {
                        "id": 6,
                        "url": "https://img.alicdn.com/imgextra/i4/112239980/O1CN0190qKUb2NatIWdxZqg_!!112239980.jpg"
                    },
                    {
                        "id": 7,
                        "url": "https://img.alicdn.com/imgextra/i1/112239980/O1CN01CIzoD22NatISvHVMi_!!112239980.jpg"
                    },
                    {
                        "id": 8,
                        "url": "https://img.alicdn.com/imgextra/i4/112239980/O1CN01iI9vtE2NatIRxPuLJ_!!112239980.jpg"
                    },
                    {
                        "id": 9,
                        "url": "https://img.alicdn.com/imgextra/i1/112239980/O1CN01iM1aey2NatIV1Oz0N_!!112239980.jpg"
                    },
                    {
                        "id": 10,
                        "url": "https://img.alicdn.com/imgextra/i1/112239980/O1CN01gvGC1H2NatINLfwpB_!!112239980.jpg"
                    },
                    {
                        "id": 11,
                        "url": "https://img.alicdn.com/imgextra/i1/112239980/O1CN01BHqhiQ2NatIXOLDZj_!!112239980.jpg"
                    },
                    {
                        "id": 12,
                        "url": "https://img.alicdn.com/imgextra/i4/112239980/O1CN01yCvEoH2NatISvIe3i_!!112239980.jpg"
                    },
                    {
                        "id": 13,
                        "url": "https://img.alicdn.com/imgextra/i1/112239980/O1CN0179eG8N2NatIUk1t0j_!!112239980.jpg"
                    },
                    {
                        "id": 14,
                        "url": "https://img.alicdn.com/imgextra/i3/112239980/O1CN01Unkx2t2NatIVD5EwU_!!112239980.jpg"
                    },
                    {
                        "id": 15,
                        "url": "https://img.alicdn.com/imgextra/i2/112239980/O1CN019RuIZP2NatIXONZ5E_!!112239980.jpg"
                    },
                    {
                        "id": 16,
                        "url": "https://img.alicdn.com/imgextra/i3/112239980/O1CN010lq9s92NatIVAZQPl_!!112239980.jpg"
                    },
                    {
                        "id": 17,
                        "url": "https://img.alicdn.com/imgextra/i4/112239980/O1CN016KX3We2NatIUSN3ZJ_!!112239980.jpg"
                    }
                ]
            }
        ]
    }
}
